autopipeline/AddNew.py
autopipeline/Filter.py
autopipeline/Interactive.py
autopipeline/Mapping.py
autopipeline/NL2SQL.py
autopipeline/PipelineExec.py
autopipeline/PipelineGen.py
autopipeline/__init__.py
autopipeline/util.py
autopipeline/data/Protective_Order.pdf
autopipeline/data/__init__.py
autopipeline/data/case_ner.csv
autopipeline/data/case_pos.csv
autopipeline/data/case_sent.csv
autopipeline/data/case_summary.csv
autopipeline/data/case_summary_ner.csv
autopipeline/data/case_summary_pos.csv
autopipeline/data/case_summary_sent.csv
autopipeline/data/desc.csv
autopipeline/data/legal-doc.csv
autopipeline/data/legal-text.csv
autopipeline/data/queries.csv
autopipeline/data/table_text.csv
autopipeline/data/table_text_ner.csv
autopipeline/data/table_text_para.csv
autopipeline/data/table_text_para_ner.csv
autopipeline/data/table_text_para_pos.csv
autopipeline/data/table_text_para_sent.csv
autopipeline/data/table_text_para_summary.csv
autopipeline/data/table_text_para_summary_sentiment.csv
autopipeline/data/table_text_pos.csv
autopipeline/data/table_text_sent.csv
autopipeline/data/table_text_summary.csv
autopipeline/data/table_text_summary_ner.csv
autopipeline/data/table_text_summary_pos.csv
autopipeline/data/table_text_summary_sent.csv
autopipeline/data/1/persuasive.csv
autopipeline/data/10/emotion_trigger.csv
autopipeline/data/11/emotion_trigger.csv
autopipeline/data/111/offensive.csv
autopipeline/data/113/translation.csv
autopipeline/data/115/ecs.csv
autopipeline/data/12/figurative.csv
autopipeline/data/13/figurative.csv
autopipeline/data/14/headlines.csv
autopipeline/data/15/dialect.csv
autopipeline/data/16/positive-reframing.csv
autopipeline/data/17/persuasive-17.csv
autopipeline/data/18/semantic.csv
autopipeline/data/19/disclosure.csv
autopipeline/data/2/emotions.csv
autopipeline/data/20/empathy.csv
autopipeline/data/21/empathy.csv
autopipeline/data/22/humor.csv
autopipeline/data/23/politeness.csv
autopipeline/data/24/toxic.csv
autopipeline/data/25/story.csv
autopipeline-0.1.398.dist-info/METADATA
autopipeline-0.1.398.dist-info/WHEEL
autopipeline-0.1.398.dist-info/top_level.txt
autopipeline-0.1.398.dist-info/RECORD
