Metadata-Version: 2.1
Name: autopipeline
Version: 0.1.398
License: LICENSE
Classifier: Programming Language :: Python :: 3
Classifier: License :: OSI Approved :: MIT License
Classifier: Operating System :: OS Independent
Requires-Dist: tiktoken
Requires-Dist: IPython
Requires-Dist: graphviz
Requires-Dist: openai
Requires-Dist: pandas
Requires-Dist: PyMuPDF
Requires-Dist: pytesseract
Requires-Dist: Pillow
Requires-Dist: gensim
Requires-Dist: nltk
Requires-Dist: textblob
Requires-Dist: scikit-learn
Requires-Dist: pandasql
Requires-Dist: spacy
Requires-Dist: requests
Requires-Dist: huggingface-hub
